calcutils/__init__.py
calcutils/calculator.py
calcutils-0.3.dist-info/METADATA
calcutils-0.3.dist-info/WHEEL
calcutils-0.3.dist-info/license
calcutils-0.3.dist-info/top_level.txt
calcutils-0.3.dist-info/RECORD
