Metadata-Version: 2.1
Name: calcutils
Version: 0.3
Summary: Utility functions for basic arithmetic calculations
Home-page: https://github.com/bashamega/py_calculator
Author: Adam Basha
Author-email: adam.webtools@gmail.com
Requires-Python: >=3.6
License-File: license
